{
  "info": {
    "_postman_id": "a1b2c3d4-e5f6-7890-abcd-ef1234567890",
    "name": "Express Products API",
    "schema": "https://schema.getpostman.com/json/collection/v2.1.0/collection.json"
  },
  "item": [
    {
      "name": "Get All Products (no filters)",
      "request": {
        "method": "GET",
        "header": [
          { "key": "x-api-key", "value": "secret_api_key_here" }
        ],
        "url": { "raw": "http://localhost:3000/api/products", "protocol": "http", "host": ["localhost"], "port": "3000", "path": ["api", "products"] }
      }
    },
    {
      "name": "Get All Products (category filter)",
      "request": {
        "method": "GET",
        "header": [
          { "key": "x-api-key", "value": "secret_api_key_here" }
        ],
        "url": { "raw": "http://localhost:3000/api/products?category=electronics", "protocol": "http", "host": ["localhost"], "port": "3000", "path": ["api", "products"], "query": [{"key": "category", "value": "electronics"}] }
      }
    },
    {
      "name": "Get All Products (search)",
      "request": {
        "method": "GET",
        "header": [
          { "key": "x-api-key", "value": "secret_api_key_here" }
        ],
        "url": { "raw": "http://localhost:3000/api/products?search=laptop", "protocol": "http", "host": ["localhost"], "port": "3000", "path": ["api", "products"], "query": [{"key": "search", "value": "laptop"}] }
      }
    },
    {
      "name": "Get All Products (pagination)",
      "request": {
        "method": "GET",
        "header": [
          { "key": "x-api-key", "value": "secret_api_key_here" }
        ],
        "url": { "raw": "http://localhost:3000/api/products?page=1&limit=2", "protocol": "http", "host": ["localhost"], "port": "3000", "path": ["api", "products"], "query": [{"key": "page", "value": "1"}, {"key": "limit", "value": "2"}] }
      }
    },
    {
      "name": "Get Product by ID",
      "request": {
        "method": "GET",
        "header": [
          { "key": "x-api-key", "value": "secret_api_key_here" }
        ],
        "url": { "raw": "http://localhost:3000/api/products/1", "protocol": "http", "host": ["localhost"], "port": "3000", "path": ["api", "products", "1"] }
      }
    },
    {
      "name": "Create Product",
      "request": {
        "method": "POST",
        "header": [
          { "key": "Content-Type", "value": "application/json" },
          { "key": "x-api-key", "value": "secret_api_key_here" }
        ],
        "body": {
          "mode": "raw",
          "raw": "{\n  \"name\": \"Tablet\",\n  \"description\": \"A new tablet\",\n  \"price\": 300,\n  \"category\": \"electronics\",\n  \"inStock\": true\n}"
        },
        "url": { "raw": "http://localhost:3000/api/products", "protocol": "http", "host": ["localhost"], "port": "3000", "path": ["api", "products"] }
      }
    },
    {
      "name": "Update Product",
      "request": {
        "method": "PUT",
        "header": [
          { "key": "Content-Type", "value": "application/json" },
          { "key": "x-api-key", "value": "secret_api_key_here" }
        ],
        "body": {
          "mode": "raw",
          "raw": "{\n  \"price\": 350\n}"
        },
        "url": { "raw": "http://localhost:3000/api/products/1", "protocol": "http", "host": ["localhost"], "port": "3000", "path": ["api", "products", "1"] }
      }
    },
    {
      "name": "Delete Product",
      "request": {
        "method": "DELETE",
        "header": [
          { "key": "x-api-key", "value": "secret_api_key_here" }
        ],
        "url": { "raw": "http://localhost:3000/api/products/1", "protocol": "http", "host": ["localhost"], "port": "3000", "path": ["api", "products", "1"] }
      }
    },
    {
      "name": "Get Product Stats",
      "request": {
        "method": "GET",
        "header": [
          { "key": "x-api-key", "value": "secret_api_key_here" }
        ],
        "url": { "raw": "http://localhost:3000/api/products/stats", "protocol": "http", "host": ["localhost"], "port": "3000", "path": ["api", "products", "stats"] }
      }
    }
  ]
}
